sairyscan/__init__.py
sairyscan/api/__init__.py
sairyscan/api/api.py
sairyscan/api/factory.py
sairyscan/api/pipeline.py
sairyscan/cli/__init__.py
sairyscan/cli/airyscan.py
sairyscan/core/__init__.py
sairyscan/core/_observers.py
sairyscan/core/io.py
sairyscan/core/settings.py
sairyscan/data/__init__.py
sairyscan/data/celegans_airyscan.czi
sairyscan/enhancing/__init__.py
sairyscan/enhancing/_psfs.py
sairyscan/enhancing/gaussian.py
sairyscan/enhancing/interface.py
sairyscan/enhancing/richardson_lucy.py
sairyscan/enhancing/spitfire_deconv.py
sairyscan/enhancing/spitfire_denoise.py
sairyscan/enhancing/wiener.py
sairyscan/reconstruction/__init__.py
sairyscan/reconstruction/_detectors_weights.py
sairyscan/reconstruction/_sure.py
sairyscan/reconstruction/ifed.py
sairyscan/reconstruction/ifed_denoising.py
sairyscan/reconstruction/interface.py
sairyscan/reconstruction/isfed.py
sairyscan/reconstruction/isfed_denoising.py
sairyscan/reconstruction/ism.py
sairyscan/reconstruction/pseudo_confocal.py
sairyscan/reconstruction/spitfire_flow.py
sairyscan/reconstruction/spitfire_join_deconv.py
sairyscan/reconstruction/spitfire_join_denoise.py
sairyscan/registration/__init__.py
sairyscan/registration/fourier_phase.py
sairyscan/registration/interface.py
sairyscan/registration/mse_registration.py
sairyscan/registration/position.py
sairyscan-0.0.3.dist-info/LICENSE
sairyscan-0.0.3.dist-info/METADATA
sairyscan-0.0.3.dist-info/WHEEL
sairyscan-0.0.3.dist-info/entry_points.txt
sairyscan-0.0.3.dist-info/top_level.txt
sairyscan-0.0.3.dist-info/RECORD
