Metadata-Version: 2.1
Name: sairyscan
Version: 0.0.3
Summary: Airyscan multi-array detector high resolution image reconstruction
Home-page: https://github.com/sylvainprigent/sairyscan
Author: Sylvain Prigent
Author-email: meriadec.prigent@gmail.com
License: BSD-3-Clause
Classifier: Development Status :: 2 - Pre-Alpha
Classifier: Intended Audience :: Developers
Classifier: Topic :: Software Development :: Testing
Classifier: Programming Language :: Python
Classifier: Programming Language :: Python :: 3
Classifier: Programming Language :: Python :: 3.10
Classifier: Programming Language :: Python :: 3.11
Classifier: Operating System :: OS Independent
Classifier: License :: OSI Approved :: BSD License
Requires-Python: >=3.10
License-File: LICENSE
Requires-Dist: scipy>=1.14.1
Requires-Dist: numpy==1.26.4
Requires-Dist: torch==2.2.1
Requires-Dist: torchvision>=0.17.1
Requires-Dist: scikit-image>=0.24.0
Requires-Dist: aicspylibczi
Provides-Extra: testing
Requires-Dist: tox; extra == "testing"
Requires-Dist: pytest; extra == "testing"
Requires-Dist: pytest-cov; extra == "testing"
